mantic/__init__.py
mantic/actions/__init__.py
mantic/actions/_build_signatures.py
mantic/actions/_bump_version.py
mantic/actions/_check_deprecated.py
mantic/actions/_check_version.py
mantic/actions/_parse_files.py
mantic/actions/check_signature.py
mantic/domain/__init__.py
mantic/domain/_argument.py
mantic/domain/_exit.py
mantic/domain/_signature.py
mantic/domain/_suffix.py
mantic/domain/_to_value.py
mantic/domain/_version.py
mantic/infra/__init__.py
mantic/infra/logs.py
mantic/infra/repo/__init__.py
mantic/infra/repo/files.py
mantic/infra/repo/versions.py
mantic/types.py
mantic/utils/__init__.py
mantic/utils/_arrays.py
mantic/utils/_functions.py
mantic_cli/__init__.py
mantic_cli/__main__.py
mantic_cli/config.py
mantic_cli/tasks/__init__.py
mantic_cli/tasks/_check_deprecated.py
mantic_cli/tasks/_check_version.py
mantic_cli/tasks/_task.py
mantic_cli/tasks/_tasks.py
mantic_cli/types.py
mantic_cli/views/__init__.py
mantic_cli/views/_base.py
mantic_cli/views/_theme.py
mantic_cli/views/_to_options.py
mantic_cli/views/help_view.py
mantic_cli/views/home_view.py
mantic_hypothesis/__init__.py
mantic-2.0.0.dist-info/entry_points.txt
mantic-2.0.0.dist-info/LICENSE
mantic-2.0.0.dist-info/WHEEL
mantic-2.0.0.dist-info/METADATA
mantic-2.0.0.dist-info/RECORD
