Metadata-Version: 2.1
Name: mantic
Version: 2.0.0
Summary: Command-line tools to facilitate se-mantic versioning.
Home-page: https://github.com/maukoquiroga/mantic
License: EUPL-1.2-or-later
Author: Mauko Quiroga
Author-email: mauko@pm.me
Maintainer: Mauko Quiroga
Maintainer-email: mauko@pm.me
Requires-Python: >=3.7,<3.10
Classifier: License :: Other/Proprietary License
Classifier: Programming Language :: Python :: 3
Classifier: Programming Language :: Python :: 3.7
Classifier: Programming Language :: Python :: 3.8
Classifier: Programming Language :: Python :: 3.9
Requires-Dist: GitPython (<4)
Requires-Dist: classes (<1)
Requires-Dist: deal (<5)
Requires-Dist: invoke (<2)
Requires-Dist: nptyping (<2)
Requires-Dist: numpy (>=1.7,<1.22)
Requires-Dist: returns (<1)
Requires-Dist: rich (<11)
Requires-Dist: termcolor (<2)
Requires-Dist: toml (<1)
Requires-Dist: typical (<3)
Requires-Dist: typing_extensions (<4); python_version >= "3.7" and python_version < "3.8"
Project-URL: Documentation, https://mantic.readthedocs.io
Project-URL: Repository, https://github.com/maukoquiroga/mantic
